MANIFEST.in
README.md
requirements-dev.txt
requirements.txt
setup.cfg
setup.py
src/vater/__about__.py
src/vater/__init__.py
src/vater/api_request.py
src/vater/cli.py
src/vater/client.py
src/vater/errors.py
src/vater/models.py
src/vater/request_types.py
src/vater/validators.py
src/vater.egg-info/PKG-INFO
src/vater.egg-info/SOURCES.txt
src/vater.egg-info/dependency_links.txt
src/vater.egg-info/entry_points.txt
src/vater.egg-info/requires.txt
src/vater.egg-info/top_level.txt
tests/__init__.py
tests/conftest.py
tests/integration_tests.py
tests/test_cli.py
tests/test_client.py