Metadata-Version: 2.1
Name: vater
Version: 0.1.1
Summary: Client for polish VAT payers register API
Home-page: UNKNOWN
Author: myslak71
Author-email: myslak@protonmail.com
License: MIT
Download-URL: https://github.com/myslak71/vater/archive/v0.1.1.tar.gz
Keywords: vat,client,api
Platform: UNKNOWN
Classifier: Development Status :: 3 - Alpha
Classifier: Intended Audience :: Developers
Classifier: Natural Language :: English
Classifier: License :: OSI Approved :: MIT License
Classifier: Programming Language :: Python
Classifier: Programming Language :: Python :: 3.8
Classifier: Programming Language :: Python :: 3.7
Requires-Python: >=3.7
Provides-Extra: dev
